cryptopp/__init__.py
cryptopp/config.ini
cryptopp/cryptopp.py
cryptopp-1.0.5.dist-info/LICENSE
cryptopp-1.0.5.dist-info/METADATA
cryptopp-1.0.5.dist-info/WHEEL
cryptopp-1.0.5.dist-info/entry_points.txt
cryptopp-1.0.5.dist-info/top_level.txt
cryptopp-1.0.5.dist-info/RECORD
