Metadata-Version: 2.1
Name: cryptopp
Version: 1.0.5
Summary: Command line Cryptocurrency Portfolio
Home-page: https://github.com/GordianSimpul/cryptopp
Author: GordianSimpul/huwwp
Author-email: gordian@simpul.me
License: GPLv3
Keywords: crypto cli portfolio curses cryptocurrency bitcoin
Classifier: Programming Language :: Python
Classifier: Programming Language :: Python :: 3
License-File: LICENSE
Requires-Dist: requests
Requires-Dist: requests-cache
